{
  "artifact": "hadron_source_backend_source_dag",
  "claim": "SOURCE_PROTOTYPE_NOT_PROMOTED",
  "claim_tier": "H2",
  "comparison_data_excluded": true,
  "forbidden_targets": [
    "CODATA_ALPHA",
    "MUON_G_MINUS_2",
    "EE_TO_HADRONS",
    "RARE_DECAY_DATA",
    "HADRON_MASS_TARGETS",
    "PDG_QCD_FITS"
  ],
  "no_target_leak_status": "PASS_EMPTY_COMPARISON_DAG",
  "required_missing_source_objects": [
    "QCD_SOURCE_PARAMETER_MAP",
    "OPH_QCD_QUOTIENT_ENSEMBLE_LAW",
    "EUCLIDEAN_QCD_SLAB_TRANSFER",
    "WARD_CURRENT_NORMALIZATION_LEDGER",
    "POSITIVE_STIELTJES_JACOBI_EXPORT",
    "SAME_SCHEME_XI_REMAINDER"
  ],
  "source_inputs": {
    "D10_QCD_DESCENDANT": "particles/runs/qcd/lambda_msbar_descendant.json",
    "OPH_PIXEL_SOURCE": "P",
    "lambda_msbar_source_inputs": {
      "alpha3_mz": 0.11833722886741345,
      "m_b_threshold_gev": 3.82011787992005,
      "m_c_threshold_gev": 1.2566920642121726,
      "mu_source_gev": 91.65246028560671
    }
  }
}
